Workbook

Sheet SALES BY MONTH
A3: Sum of Final Price | B3: Sales Rep
A4: Month | B4: Adity Rao | C4: Aman Shah | D4: Amol Sharma | E4: Komal Sharma | F4: Neha Singh | G4: Priya Mehta | H4: Rajesh Nair | I4: Rohit Kholi | J4: Grand Total
A5: Jan | B5: 6525.5 | C5: 5657 | D5: 13947 | E5: 14834 | F5: 6470 | G5: 3875 | H5: 5012.5 | I5: 8235 | J5: 64556
A6: Feb | B6: 4943 | C6: 8755.5 | D6: 7843.5 | E6: 7438 | F6: 13056 | G6: 9048 | H6: 6616.8 | I6: 3022 | J6: 60722.8
A7: Mar | B7: 6442 | C7: 6577 | D7: 12988 | E7: 11751 | F7: 3746 | G7: 2926 | H7: 4172 | I7: 9500 | J7: 58102
A8: Apr | B8: 9030 | C8: 5228 | D8: 17053.5 | E8: 7975 | F8: 9817.5 | G8: 5662 | H8: 5015 | I8: 3450 | J8: 63231
A9: May | B9: 4016 | C9: 6316 | D9: 4050 | E9: 7629.8 | F9: 9943.5 | G9: 11786.25 | H9: 11613.25 | I9: 7233 | J9: 62587.8
A10: Jun | B10: 7895 | C10: 5394 | D10: 4936 | E10: 4693 | F10: 4092 | G10: 5953.2 | H10: 12975 | I10: 10070.05 | J10: 56008.25
A11: Jul | B11: 6070 | C11: 4771 | D11: 8658 | E11: 10984 | F11: 14492.25 | G11: 3897.25 | H11: 6644.8 | I11: 5013 | J11: 60530.3
A12: Aug | B12: 2985 | C12: 15561 | D12: 6714 | E12: 4006 | F12: 3925 | G12: 8700 | H12: 14153 | I12: 3980 | J12: 60024
A13: Sep | B13: 9504 | C13: 5134 | D13: 6602 | E13: 6626.25 | F13: 5785.5 | G13: 8358 | H13: 8851 | I13: 10075 | J13: 60935.75
A14: Oct | B14: 9261 | C14: 6381.2 | D14: 9530 | E14: 9954 | F14: 11349 | G14: 4714 | H14: 12394 | I14: 4999 | J14: 68582.2
A15: Nov | B15: 4322.8 | C15: 8418 | D15: 7762.2 | E15: 6205 | F15: 6922.25 | G15: 13165 | H15: 9373.25 | I15: 6735 | J15: 62903.5
A16: Dec | B16: 12000 | C16: 9457.45 | D16: 3516 | E16: 4826 | F16: 4926 | G16: 5780 | H16: 20401 | I16: 6396 | J16: 67302.45
A17: Grand Total | B17: 82994.3 | C17: 87650.15 | D17: 103600.2 | E17: 96922.05 | F17: 94525 | G17: 83864.7 | H17: 117221.6 | I17: 78708.05 | J17: 745486.05

Sheet SALES DATA
A1: Medicare Pharma Distributors Pvt. Ltd.
A3: Invoice No | B3: Date | C3: Month | D3: Sales Rep | E3: Region | F3: Customer ID | G3: Company Name | H3: Company Representative Name | I3: Products | J3: Batch No | K3: Expiry | L3: Qty | M3: Price/Unit | N3: Total | O3: Discount | P3: Final Price
A4: 101 | B4: 45384 | C4: =TEXT(B4,"mmm") -> Apr | D4: Rajesh Nair | E4: North | F4: C101 | G4: =VLOOKUP(F4,'CUSTOMER INFO'!B3:D10,2,FALSE) -> Shree Medical & General Store | H4: =VLOOKUP(F4,'CUSTOMER INFO'!B3:D10,3,FALSE) -> Abhijeet Kulkarni | I4: Paracetamol 650mg | J4: B23P650 | K4: 46357 | L4: 50 | M4: 18 | N4: =L4*M4 -> 900 | O4: =IF(L4>=60,"Y","N") -> N | P4: =IF(L4>=60,0.95*N4,N4) -> 900
A5: 102 | B5: 45384 | C5: =TEXT(B5,"mmm") -> Apr | D5: Neha Singh | E5: West | F5: C132 | G5: =VLOOKUP(F5,'CUSTOMER INFO'!B4:D11,2,FALSE) -> JeevanCare Medical Store | H5: =VLOOKUP(F5,'CUSTOMER INFO'!B4:D11,3,FALSE) -> Neha Patel | I5: Cough Syrup 100ml | J5: B19CS01 | K5: 46235 | L5: 30 | M5: 75 | N5: =L5*M5 -> 2250 | O5: =IF(L5>=60,"Y","N") -> N | P5: =IF(L5>=60,0.95*N5,N5) -> 2250
A6: 103 | B6: 45385 | C6: =TEXT(B6,"mmm") -> Apr | D6: Adity Rao | E6: South | F6: C140 | G6: =VLOOKUP(F6,'CUSTOMER INFO'!B5:D12,2,FALSE) -> Arogya Medical & General | H6: =VLOOKUP(F6,'CUSTOMER INFO'!B5:D12,3,FALSE) -> Hrishkesh Jadhv | I6: Vitamin C Tablets | J6: B22VC10 | K6: 45870 | L6: 40 | M6: 55 | N6: =L6*M6 -> 2200 | O6: =IF(L6>=60,"Y","N") -> N | P6: =IF(L6>=60,0.95*N6,N6) -> 2200
A7: 104 | B7: 45386 | C7: =TEXT(B7,"mmm") -> Apr | D7: Priya Mehta | E7: East | F7: C150 | G7: =VLOOKUP(F7,'CUSTOMER INFO'!B6:D13,2,FALSE) -> MedEase | H7: =VLOOKUP(F7,'CUSTOMER INFO'!B6:D13,3,FALSE) -> Siddant Patil | I7: Amoxicillin 500mg | J7: B21AX50 | K7: 46266 | L7: 35 | M7: 32 | N7: =L7*M7 -> 1120 | O7: =IF(L7>=60,"Y","N") -> N | P7: =IF(L7>=60,0.95*N7,N7) -> 1120
A8: 105 | B8: 45387 | C8: =TEXT(B8,"mmm") -> Apr | D8: Amol Sharma | E8: North | F8: C157 | G8: =VLOOKUP(F8,'CUSTOMER INFO'!B7:D14,2,FALSE) -> CityMed Pharmacy | H8: =VLOOKUP(F8,'CUSTOMER INFO'!B7:D14,3,FALSE) -> Vikram Shah | I8: Hand Sanitizer 200ml | J8: B20HS20 | K8: 46357 | L8: 60 | M8: 90 | N8: =L8*M8 -> 5400 | O8: =IF(L8>=60,"Y","N") -> Y | P8: =IF(L8>=60,0.95*N8,N8) -> 5130
A9: 106 | B9: 45388 | C9: =TEXT(B9,"mmm") -> Apr | D9: Rohit Kholi | E9: West | F9: C201 | G9: =VLOOKUP(F9,'CUSTOMER INFO'!B8:D15,2,FALSE) -> TrustCare Medicals | H9: =VLOOKUP(F9,'CUSTOMER INFO'!B8:D15,3,FALSE) -> Pooja Sharma | I9: ORS Powder | J9: B23OR01 | K9: 46296 | L9: 55 | M9: 20 | N9: =L9*M9 -> 1100 | O9: =IF(L9>=60,"Y","N") -> N | P9: =IF(L9>=60,0.95*N9,N9) -> 1100
A10: 107 | B10: 45389 | C10: =TEXT(B10,"mmm") -> Apr | D10: Aman Shah | E10: South | F10: C245 | G10: =VLOOKUP(F10,'CUSTOMER INFO'!B9:D16,2,FALSE) -> Lifeline Medicals | H10: =VLOOKUP(F10,'CUSTOMER INFO'!B9:D16,3,FALSE) -> Harshal Singh | I10: Zinc Tablets | J10: B22ZC05 | K10: 46083 | L10: 25 | M10: 35 | N10: =L10*M10 -> 875 | O10: =IF(L10>=60,"Y","N") -> N | P10: =IF(L10>=60,0.95*N10,N10) -> 875
A11: 108 | B11: 45390 | C11: =TEXT(B11,"mmm") -> Apr | D11: Komal Sharma | E11: East | F11: C160 | G11: =VLOOKUP(F11,'CUSTOMER INFO'!B10:D17,2,FALSE) -> CarePlus Medical Store | H11: =VLOOKUP(F11,'CUSTOMER INFO'!B10:D17,3,FALSE) -> Riya Mishra | I11: Vitamin D3 60k | J11: B21VD60 | K11: 46381 | L11: 35 | M11: 42 | N11: =L11*M11 -> 1470 | O11: =IF(L11>=60,"Y","N") -> N | P11: =IF(L11>=60,0.95*N11,N11) -> 1470
A12: 109 | B12: 45391 | C12: =TEXT(B12,"mmm") -> Apr | D12: Rajesh Nair | E12: North | F12: C101 | G12: =VLOOKUP(F12,'CUSTOMER INFO'!B3:D10,2,FALSE) -> Shree Medical & General Store | H12: =VLOOKUP(F12,'CUSTOMER INFO'!B3:D10,3,FALSE) -> Abhijeet Kulkarni | I12: Antacid Tablets | J12: B21AC04 | K12: 46115 | L12: 45 | M12: 22 | N12: =L12*M12 -> 990 | O12: =IF(L12>=60,"Y","N") -> N | P12: =IF(L12>=60,0.95*N12,N12) -> 990
A13: 110 | B13: 45392 | C13: =TEXT(B13,"mmm") -> Apr | D13: Neha Singh | E13: West | F13: C132 | G13: =VLOOKUP(F13,'CUSTOMER INFO'!B4:D11,2,FALSE) -> JeevanCare Medical Store | H13: =VLOOKUP(F13,'CUSTOMER INFO'!B4:D11,3,FALSE) -> Neha Patel | I13: Ciprofloxacin 500mg | J13: B23CF50 | K13: 46178 | L13: 38 | M13: 48 | N13: =L13*M13 -> 1824 | O13: =IF(L13>=60,"Y","N") -> N | P13: =IF(L13>=60,0.95*N13,N13) -> 1824
A14: 111 | B14: 45393 | C14: =TEXT(B14,"mmm") -> Apr | D14: Adity Rao | E14: South | F14: C140 | G14: =VLOOKUP(F14,'CUSTOMER INFO'!B5:D12,2,FALSE) -> Arogya Medical & General | H14: =VLOOKUP(F14,'CUSTOMER INFO'!B5:D12,3,FALSE) -> Hrishkesh Jadhv | I14: Antibiotic Ointment | J14: B23AO10 | K14: 46297 | L14: 52 | M14: 95 | N14: =L14*M14 -> 4940 | O14: =IF(L14>=60,"Y","N") -> N | P14: =IF(L14>=60,0.95*N14,N14) -> 4940
A15: 112 | B15: 45394 | C15: =TEXT(B15,"mmm") -> Apr | D15: Priya Mehta | E15: East | F15: C150 | G15: =VLOOKUP(F15,'CUSTOMER INFO'!B6:D13,2,FALSE) -> MedEase | H15: =VLOOKUP(F15,'CUSTOMER INFO'!B6:D13,3,FALSE) -> Siddant Patil | I15: Paracetamol 650mg | J15: B23P651 | K15: 46357 | L15: 54 | M15: 18 | N15: =L15*M15 -> 972 | O15: =IF(L15>=60,"Y","N") -> N | P15: =IF(L15>=60,0.95*N15,N15) -> 972
A16: 113 | B16: 45395 | C16: =TEXT(B16,"mmm") -> Apr | D16: Amol Sharma | E16: North | F16: C157 | G16: =VLOOKUP(F16,'CUSTOMER INFO'!B7:D14,2,FALSE) -> CityMed Pharmacy | H16: =VLOOKUP(F16,'CUSTOMER INFO'!B7:D14,3,FALSE) -> Vikram Shah | I16: Cough Syrup 100ml | J16: B19CS02 | K16: 46235 | L16: 56 | M16: 75 | N16: =L16*M16 -> 4200 | O16: =IF(L16>=60,"Y","N") -> N | P16: =IF(L16>=60,0.95*N16,N16) -> 4200
A17: 114 | B17: 45396 | C17: =TEXT(B17,"mmm") -> Apr | D17: Rohit Kholi | E17: West | F17: C201 | G17: =VLOOKUP(F17,'CUSTOMER INFO'!B8:D15,2,FALSE) -> TrustCare Medicals | H17: =VLOOKUP(F17,'CUSTOMER INFO'!B8:D15,3,FALSE) -> Pooja Sharma | I17: Vitamin C Tablets | J17: B22VC11 | K17: 45870 | L17: 28 | M17: 55 | N17: =L17*M17 -> 1540 | O17: =IF(L17>=60,"Y","N") -> N | P17: =IF(L17>=60,0.95*N17,N17) -> 1540
A18: 115 | B18: 45397 | C18: =TEXT(B18,"mmm") -> Apr | D18: Aman Shah | E18: North | F18: C245 | G18: =VLOOKUP(F18,'CUSTOMER INFO'!B9:D16,2,FALSE) -> Lifeline Medicals | H18: =VLOOKUP(F18,'CUSTOMER INFO'!B9:D16,3,FALSE) -> Harshal Singh | I18: Amoxicillin 500mg | J18: B21AX51 | K18: 46266 | L18: 54 | M18: 32 | N18: =L18*M18 -> 1728 | O18: =IF(L18>=60,"Y","N") -> N | P18: =IF(L18>=60,0.95*N18,N18) -> 1728
A19: 116 | B19: 45398 | C19: =TEXT(B19,"mmm") -> Apr | D19: Komal Sharma | E19: West | F19: C160 | G19: =VLOOKUP(F19,'CUSTOMER INFO'!B10:D17,2,FALSE) -> CarePlus Medical Store | H19: =VLOOKUP(F19,'CUSTOMER INFO'!B10:D17,3,FALSE) -> Riya Mishra | I19: Hand Sanitizer 200ml | J19: B20HS21 | K19: 46357 | L19: 60 | M19: 90 | N19: =L19*M19 -> 5400 | O19: =IF(L19>=60,"Y","N") -> Y | P19: =IF(L19>=60,0.95*N19,N19) -> 5130
A20: 117 | B20: 45399 | C20: =TEXT(B20,"mmm") -> Apr | D20: Rajesh Nair | E20: South | F20: C101 | G20: =VLOOKUP(F20,'CUSTOMER INFO'!B3:D10,2,FALSE) -> Shree Medical & General Store | H20: =VLOOKUP(Table1[[#This Row],[Customer ID]],'CUSTOMER INFO'!B3:D10,3,FALSE) -> Abhijeet Kulkarni | I20: ORS Powder | J20: B23OR02 | K20: 46296 | L20: 55 | M20: 20 | N20: =L20*M20 -> 1100 | O20: =IF(L20>=60,"Y","N") -> N | P20: =IF(L20>=60,0.95*N20,N20) -> 1100
A21: 118 | B21: 45400 | C21: =TEXT(B21,"mmm") -> Apr | D21: Rajesh Nair | E21: East | F21: C132 | G21: =VLOOKUP(F21,'CUSTOMER INFO'!B4:D11,2,FALSE) -> JeevanCare Medical Store | H21: =VLOOKUP(Table1[[#This Row],[Customer ID]],'CUSTOMER INFO'!B4:D11,3,FALSE) -> Neha Patel | I21: Zinc Tablets | J21: B22ZC06 | K21: 46083 | L21: 35 | M21: 35 | N21: =L21*M21 -> 1225 | O21: =IF(L21>=60,"Y","N") -> N | P21: =IF(L21>=60,0.95*N21,N21) -> 1225
A22: 119 | B22: 45401 | C22: =TEXT(B22,"mmm") -> Apr | D22: Neha Singh | E22: North | F22: C140 | G22: =VLOOKUP(F22,'CUSTOMER INFO'!B5:D12,2,FALSE) -> Arogya Medical & General | H22: =VLOOKUP(Table1[[#This Row],[Customer ID]],'CUSTOMER INFO'!B5:D12,3,FALSE) -> Hrishkesh Jadhv | I22: Paracetamol 650mg | J22: B23P651 | K22: 46381 | L22: 65 | M22: 42 | N22: =L22*M22 -> 2730 | O22: =IF(L22>=60,"Y","N") -> Y | P22: =IF(L22>=60,0.95*N22,N22) -> 2593.5
A23: 120 | B23: 45402 | C23: =TEXT(B23,"mmm") -> Apr | D23: Adity Rao | E23: West | F23: C150 | G23: =VLOOKUP(F23,'CUSTOMER INFO'!B6:D13,2,FALSE) -> MedEase | H23: =VLOOKUP(Table1[[#This Row],[Customer ID]],'CUSTOMER INFO'!B6:D13,3,FALSE) -> Siddant Patil | I23: Cough Syrup 100ml | J23: B19CS02 | K23: 46115 | L23: 45 | M23: 22 | N23: =L23*M23 -> 990 | O23: =IF(L23>=60,"Y","N") -> N | P23: =IF(L23>=60,0.95*N23,N23) -> 990
A24: 121 | B24: 45403 | C24: =TEXT(B24,"mmm") -> Apr | D24: Priya Mehta | E24: South | F24: C157 | G24: =VLOOKUP(F24,'CUSTOMER INFO'!B7:D14,2,FALSE) -> CityMed Pharmacy | H24: =VLOOKUP(Table1[[#This Row],[Customer ID]],'CUSTOMER INFO'!B7:D14,3,FALSE) -> Vikram Shah | I24: Vitamin C Tablets | J24: B22VC11 | K24: 46178 | L24: 35 | M24: 48 | N24: =L24*M24 -> 1680 | O24: =IF(L24>=60,"Y","N") -> N | P24: =IF(L24>=60,0.95*N24,N24) -> 1680
A25: 122 | B25: 45404 | C25: =TEXT(B25,"mmm") -> Apr | D25: Amol Sharma | E25: East | F25: C201 | G25: =VLOOKUP(F25,'CUSTOMER INFO'!B8:D15,2,FALSE) -> TrustCare Medicals | H25: =VLOOKUP(Table1[[#This Row],[Customer ID]],'CUSTOMER INFO'!B8:D15,3,FALSE) -> Pooja Sharma | I25: Amoxicillin 500mg | J25: B21AX51 | K25: 46297 | L25: 54 | M25: 95 | N25: =L25*M25 -> 5130 | O25: =IF(L25>=60,"Y","N") -> N | P25: =IF(L25>=60,0.95*N25,N25) -> 5130
A26: 123 | B26: 45405 | C26: =TEXT(B26,"mmm") -> Apr | D26: Rohit Kholi | E26: North | F26: C245 | G26: =VLOOKUP(F26,'CUSTOMER INFO'!B9:D16,2,FALSE) -> Lifeline Medicals | H26: =VLOOKUP(Table1[[#This Row],[Customer ID]],'CUSTOMER INFO'!B9:D16,3,FALSE) -> Harshal Singh | I26: Hand Sanitizer 200ml | J26: B20HS21 | K26: 46357 | L26: 45 | M26: 18 | N26: =L26*M26 -> 810 | O26: =IF(L26>=60,"Y","N") -> N | P26: =IF(L26>=60,0.95*N26,N26) -> 810
A27: 124 | B27: 45406 | C27: =TEXT(B27,"mmm") -> Apr | D27: Aman Shah | E27: West | F27: C160 | G27: =VLOOKUP(F27,'CUSTOMER INFO'!B10:D17,2,FALSE) -> CarePlus Medical Store | H27: =VLOOKUP(Table1[[#This Row],[Customer ID]],'CUSTOMER INFO'!B10:D17,3,FALSE) -> Riya Mishra | I27: ORS Powder | J27: B23OR02 | K27: 46235 | L27: 35 | M27: 75 | N27: =L27*M27 -> 2625 | O27: =IF(L27>=60,"Y","N") -> N | P27: =IF(L27>=60,0.95*N27,N27) -> 2625
A28: 125 | B28: 45407 | C28: =TEXT(B28,"mmm") -> Apr | D28: Komal Sharma | E28: South | F28: C101 | G28: =VLOOKUP(F28,'CUSTOMER INFO'!B3:D10,2,FALSE) -> Shree Medical & General Store | H28: =VLOOKUP(Table1[[#This Row],[Customer ID]],'CUSTOMER INFO'!B3:D10,3,FALSE) -> Abhijeet Kulkarni | I28: Zinc Tablets | J28: B22ZC06 | K28: 45870 | L28: 25 | M28: 55 | N28: =L28*M28 -> 1375 | O28: =IF(L28>=60,"Y","N") -> N | P28: =IF(L28>=60,0.95*N28,N28) -> 1375
A29: 126 | B29: 45408 | C29: =TEXT(B29,"mmm") -> Apr | D29: Rajesh Nair | E29: East | F29: C132 | G29: =VLOOKUP(F29,'CUSTOMER INFO'!B4:D11,2,FALSE) -> JeevanCare Medical Store | H29: =VLOOKUP(Table1[[#This Row],[Customer ID]],'CUSTOMER INFO'!B4:D11,3,FALSE) -> Neha Patel | I29: Vitamin D3 60k | J29: B21VD61 | K29: 46266 | L29: 25 | M29: 32 | N29: =L29*M29 -> 800 | O29: =IF(L29>=60,"Y","N") -> N | P29: =IF(L29>=60,0.95*N29,N29) -> 800
A30: 127 | B30: 45409 | C30: =TEXT(B30,"mmm") -> Apr | D30: Neha Singh | E30: North | F30: C140 | G30: =VLOOKUP(F30,'CUSTOMER INFO'!B5:D12,2,FALSE) -> Arogya Medical & General | H30: =VLOOKUP(Table1[[#This Row],[Customer ID]],'CUSTOMER INFO'!B5:D12,3,FALSE) -> Hrishkesh Jadhv | I30: Antacid Tablets | J30: B21AC05 | K30: 46357 | L30: 35 | M30: 90 | N30: =L30*M30 -> 3150 | O30: =IF(L30>=60,"Y","N") -> N | P30: =IF(L30>=60,0.95*N30,N30) -> 3150
A31: 128 | B31: 45410 | C31: =TEXT(B31,"mmm") -> Apr | D31: Adity Rao | E31: West | F31: C150 | G31: =VLOOKUP(F31,'CUSTOMER INFO'!B6:D13,2,FALSE) -> MedEase | H31: =VLOOKUP(Table1[[#This Row],[Customer ID]],'CUSTOMER INFO'!B6:D13,3,FALSE) -> Siddant Patil | I31: Ciprofloxacin 500mg | J31: B23CF51 | K31: 46296 | L31: 45 | M31: 20 | N31: =L31*M31 -> 900 | O31: =IF(L31>=60,"Y","N") -> N | P31: =IF(L31>=60,0.95*N31,N31) -> 900
A32: 129 | B32: 45411 | C32: =TEXT(B32,"mmm") -> Apr | D32: Priya Mehta | E32: North | F32: C157 | G32: =VLOOKUP(F32,'CUSTOMER INFO'!B7:D14,2,FALSE) -> CityMed Pharmacy | H32: =VLOOKUP(Table1[[#This Row],[Customer ID]],'CUSTOMER INFO'!B7:D14,3,FALSE) -> Vikram Shah | I32: Antibiotic Ointment | J32: B23AO11 | K32: 46083 | L32: 54 | M32: 35 | N32: =L32*M32 -> 1890 | O32: =IF(L32>=60,"Y","N") -> N | P32: =IF(L32>=60,0.95*N32,N32) -> 1890
A33: 130 | B33: 45412 | C33: =TEXT(B33,"mmm") -> Apr | D33: Amol Sharma | E33: West | F33: C201 | G33: =VLOOKUP(F33,'CUSTOMER INFO'!B8:D15,2,FALSE) -> TrustCare Medicals | H33: =VLOOKUP(Table1[[#This Row],[Customer ID]],'CUSTOMER INFO'!B8:D15,3,FALSE) -> Pooja Sharma | I33: Paracetamol 650mg | J33: B23P652 | K33: 46381 | L33: 65 | M33: 42 | N33: =L33*M33 -> 2730 | O33: =IF(L33>=60,"Y","N") -> Y | P33: =IF(L33>=60,0.95*N33,N33) -> 2593.5
A34: 131 | B34: 45413 | C34: =TEXT(B34,"mmm") -> May | D34: Rohit Kholi | E34: South | F34: C245 | G34: =VLOOKUP(F34,'CUSTOMER INFO'!B9:D16,2,FALSE) -> Lifeline Medicals | H34: =VLOOKUP(Table1[[#This Row],[Customer ID]],'CUSTOMER INFO'!B9:D16,3,FALSE) -> Harshal Singh | I34: Cough Syrup 100ml | J34: B19CS03 | K34: 46115 | L34: 45 | M34: 22 | N34: =L34*M34 -> 990 | O34: =IF(L34>=60,"Y","N") -> N | P34: =IF(L34>=60,0.95*N34,N34) -> 990
A35: 132 | B35: 45414 | C35: =TEXT(B35,"mmm") -> May | D35: Aman Shah | E35: East | F35: C160 | G35: =VLOOKUP(F35,'CUSTOMER INFO'!B10:D17,2,FALSE) -> CarePlus Medical Store | H35: =VLOOKUP(Table1[[#This Row],[Customer ID]],'CUSTOMER INFO'!B10:D17,3,FALSE) -> Riya Mishra | I35: Vitamin C Tablets | J35: B22VC12 | K35: 46178 | L35: 35 | M35: 48 | N35: =L35*M35 -> 1680 | O35: =IF(L35>=60,"Y","N") -> N | P35: =IF(L35>=60,0.95*N35,N35) -> 1680
A36: 133 | B36: 45415 | C36: =TEXT(B36,"mmm") -> May | D36: Komal Sharma | E36: North | F36: C101 | G36: =VLOOKUP(F36,'CUSTOMER INFO'!B3:D10,2,FALSE) -> Shree Medical & General Store | H36: =VLOOKUP(Table1[[#This Row],[Customer ID]],'CUSTOMER INFO'!B3:D10,3,FALSE) -> Abhijeet Kulkarni | I36: Amoxicillin 500mg | J36: B21AX52 | K36: 46297 | L36: 45 | M36: 95 | N36: =L36*M36 -> 4275 | O36: =IF(L36>=60,"Y","N") -> N | P36: =IF(L36>=60,0.95*N36,N36) -> 4275
A37: 134 | B37: 45416 | C37: =TEXT(B37,"mmm") -> May | D37: Rajesh Nair | E37: West | F37: C132 | G37: =VLOOKUP(F37,'CUSTOMER INFO'!B4:D11,2,FALSE) -> JeevanCare Medical Store | H37: =VLOOKUP(Table1[[#This Row],[Customer ID]],'CUSTOMER INFO'!B4:D11,3,FALSE) -> Neha Patel | I37: Hand Sanitizer 200ml | J37: B20HS22 | K37: 46357 | L37: 30 | M37: 18 | N37: =L37*M37 -> 540 | O37: =IF(L37>=60,"Y","N") -> N | P37: =IF(L37>=60,0.95*N37,N37) -> 540
A38: 135 | B38: 45417 | C38: =TEXT(B38,"mmm") -> May | D38: Rajesh Nair | E38: South | F38: C140 | G38: =VLOOKUP(F38,'CUSTOMER INFO'!B5:D12,2,FALSE) -> Arogya Medical & General | H38: =VLOOKUP(Table1[[#This Row],[Customer ID]],'CUSTOMER INFO'!B5:D12,3,FALSE) -> Hrishkesh Jadhv | I38: ORS Powder | J38: B23OR03 | K38: 46235 | L38: 65 | M38: 75 | N38: =L38*M38 -> 4875 | O38: =IF(L38>=60,"Y","N") -> Y | P38: =IF(L38>=60,0.95*N38,N38) -> 4631.25
A39: 136 | B39: 45418 | C39: =TEXT(B39,"mmm") -> May | D39: Neha Singh | E39: East | F39: C150 | G39: =VLOOKUP(F39,'CUSTOMER INFO'!B6:D13,2,FALSE) -> MedEase | H39: =VLOOKUP(Table1[[#This Row],[Customer ID]],'CUSTOMER INFO'!B6:D13,3,FALSE) -> Siddant Patil | I39: Zinc Tablets | J39: B22ZC07 | K39: 45870 | L39: 35 | M39: 55 | N39: =L39*M39 -> 1925 | O39: =IF(L39>=60,"Y","N") -> N | P39: =IF(L39>=60,0.95*N39,N39) -> 1925
A40: 137 | B40: 45419 | C40: =TEXT(B40,"mmm") -> May | D40: Adity Rao | E40: North | F40: C157 | G40: =VLOOKUP(F40,'CUSTOMER INFO'!B7:D14,2,FALSE) -> CityMed Pharmacy | H40: =VLOOKUP(Table1[[#This Row],[Customer ID]],'CUSTOMER INFO'!B7:D14,3,FALSE) -> Vikram Shah | I40: Paracetamol 650mg | J40: B23P652 | K40: 46266 | L40: 55 | M40: 32 | N40: =L40*M40 -> 1760 | O40: =IF(L40>=60,"Y","N") -> N | P40: =IF(L40>=60,0.95*N40,N40) -> 1760
A41: 138 | B41: 45420 | C41: =TEXT(B41,"mmm") -> May | D41: Priya Mehta | E41: West | F41: C201 | G41: =VLOOKUP(F41,'CUSTOMER INFO'!B8:D15,2,FALSE) -> TrustCare Medicals | H41: =VLOOKUP(Table1[[#This Row],[Customer ID]],'CUSTOMER INFO'!B8:D15,3,FALSE) -> Pooja Sharma | I41: Cough Syrup 100ml | J41: B19CS03 | K41: 46357 | L41: 32 | M41: 90 | N41: =L41*M41 -> 2880 | O41: =IF(L41>=60,"Y","N") -> N | P41: =IF(L41>=60,0.95*N41,N41) -> 2880
A42: 139 | B42: 45421 | C42: =TEXT(B42,"mmm") -> May | D42: Amol Sharma | E42: South | F42: C245 | G42: =VLOOKUP(F42,'CUSTOMER INFO'!B9:D16,2,FALSE) -> Lifeline Medicals | H42: =VLOOKUP(Table1[[#This Row],[Customer ID]],'CUSTOMER INFO'!B9:D16,3,FALSE) -> Harshal Singh | I42: Vitamin C Tablets | J42: B22VC12 | K42: 46296 | L42: 48 | M42: 20 | N42: =L42*M42 -> 960 | O42: =IF(L42>=60,"Y","N") -> N | P42: =IF(L42>=60,0.95*N42,N42) -> 960
A43: 140 | B43: 45422 | C43: =TEXT(B43,"mmm") -> May | D43: Rohit Kholi | E43: East | F43: C160 | G43: =VLOOKUP(F43,'CUSTOMER INFO'!B10:D17,2,FALSE) -> CarePlus Medical Store | H43: =VLOOKUP(Table1[[#This Row],[Customer ID]],'CUSTOMER INFO'!B10:D17,3,FALSE) -> Riya Mishra | I43: Amoxicillin 500mg | J43: B21AX52 | K43: 46083 | L43: 54 | M43: 35 | N43: =L43*M43 -> 1890 | O43: =IF(L43>=60,"Y","N") -> N | P43: =IF(L43>=60,0.95*N43,N43) -> 1890
A44: 141 | B44: 45423 | C44: =TEXT(B44,"mmm") -> May | D44: Aman Shah | E44: North | F44: C101 | G44: =VLOOKUP(F44,'CUSTOMER INFO'!B3:D10,2,FALSE) -> Shree Medical & General Store | H44: =VLOOKUP(Table1[[#This Row],[Customer ID]],'CUSTOMER INFO'!B3:D10,3,FALSE) -> Abhijeet Kulkarni | I44: Hand Sanitizer 200ml | J44: B20HS22 | K44: 46381 | L44: 28 | M44: 42 | N44: =L44*M44 -> 1176 | O44: =IF(L44>=60,"Y","N") -> N | P44: =IF(L44>=60,0.95*N44,N44) -> 1176
A45: 142 | B45: 45424 | C45: =TEXT(B45,"mmm") -> May | D45: Komal Sharma | E45: West | F45: C132 | G45: =VLOOKUP(F45,'CUSTOMER INFO'!B4:D11,2,FALSE) -> JeevanCare Medical Store | H45: =VLOOKUP(Table1[[#This Row],[Customer ID]],'CUSTOMER INFO'!B4:D11,3,FALSE) -> Neha Patel | I45: ORS Powder | J45: B23OR03 | K45: 46115 | L45: 35 | M45: 22 | N45: =L45*M45 -> 770 | O45: =IF(L45>=60,"Y","N") -> N | P45: =IF(L45>=60,0.95*N45,N45) -> 770
A46: 143 | B46: 45425 | C46: =TEXT(B46,"mmm") -> May | D46: Rajesh Nair | E46: North | F46: C140 | G46: =VLOOKUP(F46,'CUSTOMER INFO'!B5:D12,2,FALSE) -> Arogya Medical & General | H46: =VLOOKUP(Table1[[#This Row],[Customer ID]],'CUSTOMER INFO'!B5:D12,3,FALSE) -> Hrishkesh Jadhv | I46: Zinc Tablets | J46: B22ZC07 | K46: 46178 | L46: 22 | M46: 48 | N46: =L46*M46 -> 1056 | O46: =IF(L46>=60,"Y","N") -> N | P46: =IF(L46>=60,0.95*N46,N46) -> 1056
A47: 144 | B47: 45426 | C47: =TEXT(B47,"mmm") -> May | D47: Neha Singh | E47: West | F47: C150 | G47: =VLOOKUP(F47,'CUSTOMER INFO'!B6:D13,2,FALSE) -> MedEase | H47: =VLOOKUP(Table1[[#This Row],[Customer ID]],'CUSTOMER INFO'!B6:D13,3,FALSE) -> Siddant Patil | I47: Vitamin D3 60k | J47: B21VD62 | K47: 46297 | L47: 62 | M47: 95 | N47: =L47*M47 -> 5890 | O47: =IF(L47>=60,"Y","N") -> Y | P47: =IF(L47>=60,0.95*N47,N47) -> 5595.5
A48: 145 | B48: 45427 | C48: =TEXT(B48,"mmm") -> May | D48: Adity Rao | E48: South | F48: C157 | G48: =VLOOKUP(F48,'CUSTOMER INFO'!B7:D14,2,FALSE) -> CityMed Pharmacy | H48: =VLOOKUP(Table1[[#This Row],[Customer ID]],'CUSTOMER INFO'!B7:D14,3,FALSE) -> Vikram Shah | I48: Antacid Tablets | J48: B21AC06 | K48: 46357 | L48: 32 | M48: 18 | N48: =L48*M48 -> 576 | O48: =IF(L48>=60,"Y","N") -> N | P48: =IF(L48>=60,0.95*N48,N48) -> 576
A49: 146 | B49: 45428 | C49: =TEXT(B49,"mmm") -> May | D49: Priya Mehta | E49: East | F49: C201 | G49: =VLOOKUP(F49,'CUSTOMER INFO'!B8:D15,2,FALSE) -> TrustCare Medicals | H49: =VLOOKUP(Table1[[#This Row],[Customer ID]],'CUSTOMER INFO'!B8:D15,3,FALSE) -> Pooja Sharma | I49: Paracetamol 650mg | J49: B23P651 | K49: 46235 | L49: 65 | M49: 75 | N49: =L49*M49 -> 4875 | O49: =IF(L49>=60,"Y","N") -> Y | P49: =IF(L49>=60,0.95*N49,N49) -> 4631.25
A50: 147 | B50: 45429 | C50: =TEXT(B50,"mmm") -> May | D50: Amol Sharma | E50: North | F50: C245 | G50: =VLOOKUP(F50,'CUSTOMER INFO'!B9:D16,2,FALSE) -> Lifeline Medicals | H50: =VLOOKUP(Table1[[#This Row],[Customer ID]],'CUSTOMER INFO'!B9:D16,3,FALSE) -> Harshal Singh | I50: Cough Syrup 100ml | J50: B19CS02 | K50: 45870 | L50: 48 | M50: 55 | N50: =L50*M50 -> 2640 | O50: =IF(L50>=60,"Y","N") -> N | P50: =IF(L50>=60,0.95*N50,N50) -> 2640
A51: 148 | B51: 45430 | C51: =TEXT(B51,"mmm") -> May | D51: Rohit Kholi | E51: West | F51: C160 | G51: =VLOOKUP(F51,'CUSTOMER INFO'!B10:D17,2,FALSE) -> CarePlus Medical Store | H51: =VLOOKUP(Table1[[#This Row],[Customer ID]],'CUSTOMER INFO'!B10:D17,3,FALSE) -> Riya Mishra | I51: Vitamin C Tablets | J51: B22VC11 | K51: 46266 | L51: 54 | M51: 32 | N51: =L51*M51 -> 1728 | O51: =IF(L51>=60,"Y","N") -> N | P51: =IF(L51>=60,0.95*N51,N51) -> 1728
A52: 149 | B52: 45431 | C52: =TEXT(B52,"mmm") -> May | D52: Aman Shah | E52: South | F52: C101 | G52: =VLOOKUP(F52,'CUSTOMER INFO'!B3:D10,2,FALSE) -> Shree Medical & General Store | H52: =VLOOKUP(Table1[[#This Row],[Customer ID]],'CUSTOMER INFO'!B3:D10,3,FALSE) -> Abhijeet Kulkarni | I52: Amoxicillin 500mg | J52: B21AX51 | K52: 46357 | L52: 25 | M52: 90 | N52: =L52*M52 -> 2250 | O52: =IF(L52>=60,"Y","N") -> N | P52: =IF(L52>=60,0.95*N52,N52) -> 2250
A53: 150 | B53: 45432 | C53: =TEXT(B53,"mmm") -> May | D53: Komal Sharma | E53: East | F53: C132 | G53: =VLOOKUP(F53,'CUSTOMER INFO'!B4:D11,2,FALSE) -> JeevanCare Medical Store | H53: =VLOOKUP(Table1[[#This Row],[Customer ID]],'CUSTOMER INFO'!B4:D11,3,FALSE) -> Neha Patel | I53: Hand Sanitizer 200ml | J53: B20HS21 | K53: 46296 | L53: 35 | M53: 20 | N53: =L53*M53 -> 700 | O53: =IF(L53>=60,"Y","N") -> N | P53: =IF(L53>=60,0.95*N53,N53) -> 700
A54: 151 | B54: 45433 | C54: =TEXT(B54,"mmm") -> May | D54: Rajesh Nair | E54: North | F54: C140 | G54: =VLOOKUP(F54,'CUSTOMER INFO'!B5:D12,2,FALSE) -> Arogya Medical & General | H54: =VLOOKUP(Table1[[#This Row],[Customer ID]],'CUSTOMER INFO'!B5:D12,3,FALSE) -> Hrishkesh Jadhv | I54: ORS Powder | J54: B23OR02 | K54: 46083 | L54: 38 | M54: 35 | N54: =L54*M54 -> 1330 | O54: =IF(L54>=60,"Y","N") -> N | P54: =IF(L54>=60,0.95*N54,N54) -> 1330
A55: 152 | B55: 45434 | C55: =TEXT(B55,"mmm") -> May | D55: Rajesh Nair | E55: West | F55: C150 | G55: =VLOOKUP(F55,'CUSTOMER INFO'!B6:D13,2,FALSE) -> MedEase | H55: =VLOOKUP(Table1[[#This Row],[Customer ID]],'CUSTOMER INFO'!B6:D13,3,FALSE) -> Siddant Patil | I55: Zinc Tablets | J55: B22ZC06 | K55: 46381 | L55: 28 | M55: 42 | N55: =L55*M55 -> 1176 | O55: =IF(L55>=60,"Y","N") -> N | P55: =IF(L55>=60,0.95*N55,N55) -> 1176
A56: 153 | B56: 45435 | C56: =TEXT(B56,"mmm") -> May | D56: Neha Singh | E56: South | F56: C157 | G56: =VLOOKUP(F56,'CUSTOMER INFO'!B7:D14,2,FALSE) -> CityMed Pharmacy | H56: =VLOOKUP(Table1[[#This Row],[Customer ID]],'CUSTOMER INFO'!B7:D14,3,FALSE) -> Vikram Shah | I56: Vitamin D3 60k | J56: B21VD61 | K56: 46115 | L56: 54 | M56: 22 | N56: =L56*M56 -> 1188 | O56: =IF(L56>=60,"Y","N") -> N | P56: =IF(L56>=60,0.95*N56,N56) -> 1188
A57: 154 | B57: 45436 | C57: =TEXT(B57,"mmm") -> May | D57: Adity Rao | E57: East | F57: C201 | G57: =VLOOKUP(F57,'CUSTOMER INFO'!B8:D15,2,FALSE) -> TrustCare Medicals | H57: =VLOOKUP(Table1[[#This Row],[Customer ID]],'CUSTOMER INFO'!B8:D15,3,FALSE) -> Pooja Sharma | I57: Antacid Tablets | J57: B21AC05 | K57: 46178 | L57: 35 | M57: 48 | N57: =L57*M57 -> 1680 | O57: =IF(L57>=60,"Y","N") -> N | P57: =IF(L57>=60,0.95*N57,N57) -> 1680
A58: 155 | B58: 45437 | C58: =TEXT(B58,"mmm") -> May | D58: Priya Mehta | E58: North | F58: C245 | G58: =VLOOKUP(F58,'CUSTOMER INFO'!B9:D16,2,FALSE) -> Lifeline Medicals | H58: =VLOOKUP(Table1[[#This Row],[Customer ID]],'CUSTOMER INFO'!B9:D16,3,FALSE) -> Harshal Singh | I58: Ciprofloxacin 500mg | J58: B23CF51 | K58: 46297 | L58: 45 | M58: 95 | N58: =L58*M58 -> 4275 | O58: =IF(L58>=60,"Y","N") -> N | P58: =IF(L58>=60,0.95*N58,N58) -> 4275
A59: 156 | B59: 45438 | C59: =TEXT(B59,"mmm") -> May | D59: Amol Sharma | E59: West | F59: C160 | G59: =VLOOKUP(F59,'CUSTOMER INFO'!B10:D17,2,FALSE) -> CarePlus Medical Store | H59: =VLOOKUP(Table1[[#This Row],[Customer ID]],'CUSTOMER INFO'!B10:D17,3,FALSE) -> Riya Mishra | I59: Antibiotic Ointment | J59: B23AO11 | K59: 46357 | L59: 25 | M59: 18 | N59: =L59*M59 -> 450 | O59: =IF(L59>=60,"Y","N") -> N | P59: =IF(L59>=60,0.95*N59,N59) -> 450
A60: 157 | B60: 45439 | C60: =TEXT(B60,"mmm") -> May | D60: Rohit Kholi | E60: North | F60: C101 | G60: =VLOOKUP(Table1[[#This Row],[Customer ID]],'CUSTOMER INFO'!B3:D10,2,FALSE) -> Shree Medical & General Store | H60: =VLOOKUP(Table1[[#This Row],[Customer ID]],'CUSTOMER INFO'!B3:D10,3,FALSE) -> Abhijeet Kulkarni | I60: Paracetamol 650mg | J60: B23P652 | K60: 46235 | L60: 35 | M60: 75 | N60: =L60*M60 -> 2625 | O60: =IF(L60>=60,"Y","N") -> N | P60: =IF(L60>=60,0.95*N60,N60) -> 2625
A61: 158 | B61: 45440 | C61: =TEXT(B61,"mmm") -> May | D61: Aman Shah | E61: West | F61: C132 | G61: =VLOOKUP(Table1[[#This Row],[Customer ID]],'CUSTOMER INFO'!B4:D11,2,FALSE) -> JeevanCare Medical Store | H61: =VLOOKUP(Table1[[#This Row],[Customer ID]],'CUSTOMER INFO'!B4:D11,3,FALSE) -> Neha Patel | I61: Cough Syrup 100ml | J61: B19CS03 | K61: 45870 | L61: 22 | M61: 55 | N61: =L61*M61 -> 1210 | O61: =IF(L61>=60,"Y","N") -> N | P61: =IF(L61>=60,0.95*N61,N61) -> 1210
A62: 159 | B62: 45441 | C62: =TEXT(B62,"mmm") -> May | D62: Komal Sharma | E62: South | F62: C140 | G62: =VLOOKUP(Table1[[#This Row],[Customer ID]],'CUSTOMER INFO'!B5:D12,2,FALSE) -> Arogya Medical & General | H62: =VLOOKUP(Table1[[#This Row],[Customer ID]],'CUSTOMER INFO'!B5:D12,3,FALSE) -> Hrishkesh Jadhv | I62: Vitamin C Tablets | J62: B22VC12 | K62: 46266 | L62: 62 | M62: 32 | N62: =L62*M62 -> 1984 | O62: =IF(L62>=60,"Y","N") -> Y | P62: =IF(L62>=60,0.95*N62,N62) -> 1884.8
A63: 160 | B63: 45442 | C63: =TEXT(B63,"mmm") -> May | D63: Rajesh Nair | E63: East | F63: C150 | G63: =VLOOKUP(Table1[[#This Row],[Customer ID]],'CUSTOMER INFO'!B6:D13,2,FALSE) -> MedEase | H63: =VLOOKUP(Table1[[#This Row],[Customer ID]],'CUSTOMER INFO'!B6:D13,3,FALSE) -> Siddant Patil | I63: Amoxicillin 500mg | J63: B21AX52 | K63: 46357 | L63: 32 | M63: 90 | N63: =L63*M63 -> 2880 | O63: =IF(L63>=60,"Y","N") -> N | P63: =IF(L63>=60,0.95*N63,N63) -> 2880
A64: 161 | B64: 45443 | C64: =TEXT(B64,"mmm") -> May | D64: Neha Singh | E64: North | F64: C157 | G64: =VLOOKUP(Table1[[#This Row],[Customer ID]],'CUSTOMER INFO'!B7:D14,2,FALSE) -> CityMed Pharmacy | H64: =VLOOKUP(Table1[[#This Row],[Customer ID]],'CUSTOMER INFO'!B7:D14,3,FALSE) -> Vikram Shah | I64: Hand Sanitizer 200ml | J64: B20HS22 | K64: 46296 | L64: 65 | M64: 20 | N64: =L64*M64 -> 1300 | O64: =IF(L64>=60,"Y","N") -> Y | P64: =IF(L64>=60,0.95*N64,N64) -> 1235
A65: 162 | B65: 45444 | C65: =TEXT(B65,"mmm") -> Jun | D65: Adity Rao | E65: West | F65: C201 | G65: =VLOOKUP(Table1[[#This Row],[Customer ID]],'CUSTOMER INFO'!B8:D15,2,FALSE) -> TrustCare Medicals | H65: =VLOOKUP(Table1[[#This Row],[Customer ID]],'CUSTOMER INFO'!B8:D15,3,FALSE) -> Pooja Sharma | I65: ORS Powder | J65: B23OR03 | K65: 46083 | L65: 48 | M65: 35 | N65: =L65*M65 -> 1680 | O65: =IF(L65>=60,"Y","N") -> N | P65: =IF(L65>=60,0.95*N65,N65) -> 1680
A66: 163 | B66: 45445 | C66: =TEXT(B66,"mmm") -> Jun | D66: Priya Mehta | E66: South | F66: C245 | G66: =VLOOKUP(Table1[[#This Row],[Customer ID]],'CUSTOMER INFO'!B9:D16,2,FALSE) -> Lifeline Medicals | H66: =VLOOKUP(Table1[[#This Row],[Customer ID]],'CUSTOMER INFO'!B9:D16,3,FALSE) -> Harshal Singh | I66: Zinc Tablets | J66: B22ZC07 | K66: 46381 | L66: 54 | M66: 42 | N66: =L66*M66 -> 2268 | O66: =IF(L66>=60,"Y","N") -> N | P66: =IF(L66>=60,0.95*N66,N66) -> 2268
A67: 164 | B67: 45446 | C67: =TEXT(B67,"mmm") -> Jun | D67: Amol Sharma | E67: East | F67: C160 | G67: =VLOOKUP(Table1[[#This Row],[Customer ID]],'CUSTOMER INFO'!B10:D17,2,FALSE) -> CarePlus Medical Store | H67: =VLOOKUP(Table1[[#This Row],[Customer ID]],'CUSTOMER INFO'!B10:D17,3,FALSE) -> Riya Mishra | I67: Paracetamol 650mg | J67: B23P652 | K67: 46115 | L67: 25 | M67: 22 | N67: =L67*M67 -> 550 | O67: =IF(L67>=60,"Y","N") -> N | P67: =IF(L67>=60,0.95*N67,N67) -> 550
A68: 165 | B68: 45447 | C68: =TEXT(B68,"mmm") -> Jun | D68: Rohit Kholi | E68: North | F68: C101 | G68: =VLOOKUP(Table1[[#This Row],[Customer ID]],'CUSTOMER INFO'!B3:D10,2,FALSE) -> Shree Medical & General Store | H68: =VLOOKUP(Table1[[#This Row],[Customer ID]],'CUSTOMER INFO'!B3:D10,3,FALSE) -> Abhijeet Kulkarni | I68: Cough Syrup 100ml | J68: B19CS03 | K68: 46178 | L68: 35 | M68: 48 | N68: =L68*M68 -> 1680 | O68: =IF(L68>=60,"Y","N") -> N | P68: =IF(L68>=60,0.95*N68,N68) -> 1680
A69: 166 | B69: 45448 | C69: =TEXT(B69,"mmm") -> Jun | D69: Aman Shah | E69: West | F69: C132 | G69: =VLOOKUP(Table1[[#This Row],[Customer ID]],'CUSTOMER INFO'!B4:D11,2,FALSE) -> JeevanCare Medical Store | H69: =VLOOKUP(Table1[[#This Row],[Customer ID]],'CUSTOMER INFO'!B4:D11,3,FALSE) -> Neha Patel | I69: Vitamin C Tablets | J69: B22VC12 | K69: 46297 | L69: 38 | M69: 95 | N69: =L69*M69 -> 3610 | O69: =IF(L69>=60,"Y","N") -> N | P69: =IF(L69>=60,0.95*N69,N69) -> 3610
A70: 167 | B70: 45449 | C70: =TEXT(B70,"mmm") -> Jun | D70: Komal Sharma | E70: South | F70: C140 | G70: =VLOOKUP(Table1[[#This Row],[Customer ID]],'CUSTOMER INFO'!B5:D12,2,FALSE) -> Arogya Medical & General | H70: =VLOOKUP(Table1[[#This Row],[Customer ID]],'CUSTOMER INFO'!B5:D12,3,FALSE) -> Hrishkesh Jadhv | I70: Amoxicillin 500mg | J70: B21AX52 | K70: 46357 | L70: 28 | M70: 18 | N70: =L70*M70 -> 504 | O70: =IF(L70>=60,"Y","N") -> N | P70: =IF(L70>=60,0.95*N70,N70) -> 504
A71: 168 | B71: 45450 | C71: =TEXT(B71,"mmm") -> Jun | D71: Rajesh Nair | E71: East | F71: C150 | G71: =VLOOKUP(Table1[[#This Row],[Customer ID]],'CUSTOMER INFO'!B6:D13,2,FALSE) -> MedEase | H71: =VLOOKUP(Table1[[#This Row],[Customer ID]],'CUSTOMER INFO'!B6:D13,3,FALSE) -> Siddant Patil | I71: Hand Sanitizer 200ml | J71: B20HS22 | K71: 46235 | L71: 54 | M71: 75 | N71: =L71*M71 -> 4050 | O71: =IF(L71>=60,"Y","N") -> N | P71: =IF(L71>=60,0.95*N71,N71) -> 4050
A72: 169 | B72: 45451 | C72: =TEXT(B72,"mmm") -> Jun | D72: Rajesh Nair | E72: North | F72: C157 | G72: =VLOOKUP(Table1[[#This Row],[Customer ID]],'CUSTOMER INFO'!B7:D14,2,FALSE) -> CityMed Pharmacy | H72: =VLOOKUP(Table1[[#This Row],[Customer ID]],'CUSTOMER INFO'!B7:D14,3,FALSE) -> Vikram Shah | I72: ORS Powder | J72: B23OR03 | K72: 45870 | L72: 35 | M72: 55 | N72: =L72*M72 -> 1925 | O72: =IF(L72>=60,"Y","N") -> N | P72: =IF(L72>=60,0.95*N72,N72) -> 1925
A73: 170 | B73: 45452 | C73: =TEXT(B73,"mmm") -> Jun | D73: Neha Singh | E73: West | F73: C201 | G73: =VLOOKUP(Table1[[#This Row],[Customer ID]],'CUSTOMER INFO'!B8:D15,2,FALSE) -> TrustCare Medicals | H73: =VLOOKUP(Table1[[#This Row],[Customer ID]],'CUSTOMER INFO'!B8:D15,3,FALSE) -> Pooja Sharma | I73: Zinc Tablets | J73: B22ZC07 | K73: 46266 | L73: 45 | M73: 32 | N73: =L73*M73 -> 1440 | O73: =IF(L73>=60,"Y","N") -> N | P73: =IF(L73>=60,0.95*N73,N73) -> 1440
A74: 171 | B74: 45453 | C74: =TEXT(B74,"mmm") -> Jun | D74: Adity Rao | E74: North | F74: C245 | G74: =VLOOKUP(Table1[[#This Row],[Customer ID]],'CUSTOMER INFO'!B9:D16,2,FALSE) -> Lifeline Medicals | H74: =VLOOKUP(Table1[[#This Row],[Customer ID]],'CUSTOMER INFO'!B9:D16,3,FALSE) -> Harshal Singh | I74: Vitamin D3 60k | J74: B21VD62 | K74: 46357 | L74: 25 | M74: 90 | N74: =L74*M74 -> 2250 | O74: =IF(L74>=60,"Y","N") -> N | P74: =IF(L74>=60,0.95*N74,N74) -> 2250
A75: 172 | B75: 45454 | C75: =TEXT(B75,"mmm") -> Jun | D75: Priya Mehta | E75: West | F75: C160 | G75: =VLOOKUP(Table1[[#This Row],[Customer ID]],'CUSTOMER INFO'!B10:D17,2,FALSE) -> CarePlus Medical Store | H75: =VLOOKUP(Table1[[#This Row],[Customer ID]],'CUSTOMER INFO'!B10:D17,3,FALSE) -> Riya Mishra | I75: Antacid Tablets | J75: B21AC06 | K75: 46296 | L75: 35 | M75: 20 | N75: =L75*M75 -> 700 | O75: =IF(L75>=60,"Y","N") -> N | P75: =IF(L75>=60,0.95*N75,N75) -> 700
A76: 173 | B76: 45455 | C76: =TEXT(B76,"mmm") -> Jun | D76: Amol Sharma | E76: South | F76: C101 | G76: =VLOOKUP(Table1[[#This Row],[Customer ID]],'CUSTOMER INFO'!B3:D10,2,FALSE) -> Shree Medical & General Store | H76: =VLOOKUP(Table1[[#This Row],[Customer ID]],'CUSTOMER INFO'!B3:D10,3,FALSE) -> Abhijeet Kulkarni | I76: Ciprofloxacin 500mg | J76: B23CF52 | K76: 46083 | L76: 22 | M76: 35 | N76: =L76*M76 -> 770 | O76: =IF(L76>=60,"Y","N") -> N | P76: =IF(L76>=60,0.95*N76,N76) -> 770
A77: 174 | B77: 45456 | C77: =TEXT(B77,"mmm") -> Jun | D77: Rohit Kholi | E77: East | F77: C132 | G77: =VLOOKUP(Table1[[#This Row],[Customer ID]],'CUSTOMER INFO'!B4:D11,2,FALSE) -> JeevanCare Medical Store | H77: =VLOOKUP(Table1[[#This Row],[Customer ID]],'CUSTOMER INFO'!B4:D11,3,FALSE) -> Neha Patel | I77: Antibiotic Ointment | J77: B23AO12 | K77: 46381 | L77: 62 | M77: 42 | N77: =L77*M77 -> 2604 | O77: =IF(L77>=60,"Y","N") -> Y | P77: =IF(L77>=60,0.95*N77,N77) -> 2473.8
A78: 175 | B78: 45457 | C78: =TEXT(B78,"mmm") -> Jun | D78: Aman Shah | E78: North | F78: C140 | G78: =VLOOKUP(Table1[[#This Row],[Customer ID]],'CUSTOMER INFO'!B5:D12,2,FALSE) -> Arogya Medical & General | H78: =VLOOKUP(Table1[[#This Row],[Customer ID]],'CUSTOMER INFO'!B5:D12,3,FALSE) -> Hrishkesh Jadhv | I78: Paracetamol 650mg | J78: B23P653 | K78: 46115 | L78: 32 | M78: 22 | N78: =L78*M78 -> 704 | O78: =IF(L78>=60,"Y","N") -> N | P78: =IF(L78>=60,0.95*N78,N78) -> 704
A79: 176 | B79: 45458 | C79: =TEXT(B79,"mmm") -> Jun | D79: Komal Sharma | E79: West | F79: C150 | G79: =VLOOKUP(Table1[[#This Row],[Customer ID]],'CUSTOMER INFO'!B6:D13,2,FALSE) -> MedEase | H79: =VLOOKUP(Table1[[#This Row],[Customer ID]],'CUSTOMER INFO'!B6:D13,3,FALSE) -> Siddant Patil | I79: Cough Syrup 100ml | J79: B19CS04 | K79: 46178 | L79: 65 | M79: 48 | N79: =L79*M79 -> 3120 | O79: =IF(L79>=60,"Y","N") -> Y | P79: =IF(L79>=60,0.95*N79,N79) -> 2964
A80: 177 | B80: 45459 | C80: =TEXT(B80,"mmm") -> Jun | D80: Rajesh Nair | E80: South | F80: C157 | G80: =VLOOKUP(Table1[[#This Row],[Customer ID]],'CUSTOMER INFO'!B7:D14,2,FALSE) -> CityMed Pharmacy | H80: =VLOOKUP(Table1[[#This Row],[Customer ID]],'CUSTOMER INFO'!B7:D14,3,FALSE) -> Vikram Shah | I80: Vitamin C Tablets | J80: B22VC13 | K80: 46297 | L80: 48 | M80: 95 | N80: =L80*M80 -> 4560 | O80: =IF(L80>=60,"Y","N") -> N | P80: =IF(L80>=60,0.95*N80,N80) -> 4560
A81: 178 | B81: 45460 | C81: =TEXT(B81,"mmm") -> Jun | D81: Neha Singh | E81: East | F81: C201 | G81: =VLOOKUP(Table1[[#This Row],[Customer ID]],'CUSTOMER INFO'!B8:D15,2,FALSE) -> TrustCare Medicals | H81: =VLOOKUP(Table1[[#This Row],[Customer ID]],'CUSTOMER INFO'!B8:D15,3,FALSE) -> Pooja Sharma | I81: Amoxicillin 500mg | J81: B21AX53 | K81: 46357 | L81: 54 | M81: 18 | N81: =L81*M81 -> 972 | O81: =IF(L81>=60,"Y","N") -> N | P81: =IF(L81>=60,0.95*N81,N81) -> 972
A82: 179 | B82: 45461 | C82: =TEXT(B82,"mmm") -> Jun | D82: Adity Rao | E82: North | F82: C245 | G82: =VLOOKUP(Table1[[#This Row],[Customer ID]],'CUSTOMER INFO'!B9:D16,2,FALSE) -> Lifeline Medicals | H82: =VLOOKUP(Table1[[#This Row],[Customer ID]],'CUSTOMER INFO'!B9:D16,3,FALSE) -> Harshal Singh | I82: Hand Sanitizer 200ml | J82: B20HS23 | K82: 46235 | L82: 25 | M82: 75 | N82: =L82*M82 -> 1875 | O82: =IF(L82>=60,"Y","N") -> N | P82: =IF(L82>=60,0.95*N82,N82) -> 1875
A83: 180 | B83: 45462 | C83: =TEXT(B83,"mmm") -> Jun | D83: Priya Mehta | E83: West | F83: C160 | G83: =VLOOKUP(Table1[[#This Row],[Customer ID]],'CUSTOMER INFO'!B10:D17,2,FALSE) -> CarePlus Medical Store | H83: =VLOOKUP(Table1[[#This Row],[Customer ID]],'CUSTOMER INFO'!B10:D17,3,FALSE) -> Riya Mishra | I83: ORS Powder | J83: B23OR04 | K83: 45870 | L83: 35 | M83: 55 | N83: =L83*M83 -> 1925 | O83: =IF(L83>=60,"Y","N") -> N | P83: =IF(L83>=60,0.95*N83,N83) -> 1925
A84: 181 | B84: 45463 | C84: =TEXT(B84,"mmm") -> Jun | D84: Amol Sharma | E84: South | F84: C101 | G84: =VLOOKUP(F84,'CUSTOMER INFO'!B3:D10,2,FALSE) -> Shree Medical & General Store | H84: =VLOOKUP(F84,'CUSTOMER INFO'!B3:D10,3,FALSE) -> Abhijeet Kulkarni | I84: Zinc Tablets | J84: B22ZC08 | K84: 46266 | L84: 38 | M84: 32 | N84: =L84*M84 -> 1216 | O84: =IF(L84>=60,"Y","N") -> N | P84: =IF(L84>=60,0.95*N84,N84) -> 1216
A85: 182 | B85: 45464 | C85: =TEXT(B85,"mmm") -> Jun | D85: Rohit Kholi | E85: East | F85: C132 | G85: =VLOOKUP(F85,'CUSTOMER INFO'!B4:D11,2,FALSE) -> JeevanCare Medical Store | H85: =VLOOKUP(F85,'CUSTOMER INFO'!B4:D11,3,FALSE) -> Neha Patel | I85: Paracetamol 650mg | J85: B23P653 | K85: 46357 | L85: 28 | M85: 90 | N85: =L85*M85 -> 2520 | O85: =IF(L85>=60,"Y","N") -> N | P85: =IF(L85>=60,0.95*N85,N85) -> 2520
A86: 183 | B86: 45465 | C86: =TEXT(B86,"mmm") -> Jun | D86: Aman Shah | E86: North | F86: C140 | G86: =VLOOKUP(F86,'CUSTOMER INFO'!B5:D12,2,FALSE) -> Arogya Medical & General | H86: =VLOOKUP(F86,'CUSTOMER INFO'!B5:D12,3,FALSE) -> Hrishkesh Jadhv | I86: Cough Syrup 100ml | J86: B19CS04 | K86: 46296 | L86: 54 | M86: 20 | N86: =L86*M86 -> 1080 | O86: =IF(L86>=60,"Y","N") -> N | P86: =IF(L86>=60,0.95*N86,N86) -> 1080
A87: 184 | B87: 45466 | C87: =TEXT(B87,"mmm") -> Jun | D87: Komal Sharma | E87: West | F87: C150 | G87: =VLOOKUP(F87,'CUSTOMER INFO'!B6:D13,2,FALSE) -> MedEase | H87: =VLOOKUP(F87,'CUSTOMER INFO'!B6:D13,3,FALSE) -> Siddant Patil | I87: Vitamin C Tablets | J87: B22VC13 | K87: 46083 | L87: 35 | M87: 35 | N87: =L87*M87 -> 1225 | O87: =IF(L87>=60,"Y","N") -> N | P87: =IF(L87>=60,0.95*N87,N87) -> 1225
A88: 185 | B88: 45467 | C88: =TEXT(B88,"mmm") -> Jun | D88: Rajesh Nair | E88: North | F88: C157 | G88: =VLOOKUP(F88,'CUSTOMER INFO'!B7:D14,2,FALSE) -> CityMed Pharmacy | H88: =VLOOKUP(F88,'CUSTOMER INFO'!B7:D14,3,FALSE) -> Vikram Shah | I88: Amoxicillin 500mg | J88: B21AX53 | K88: 46381 | L88: 45 | M88: 42 | N88: =L88*M88 -> 1890 | O88: =IF(L88>=60,"Y","N") -> N | P88: =IF(L88>=60,0.95*N88,N88) -> 1890
A89: 186 | B89: 45468 | C89: =TEXT(B89,"mmm") -> Jun | D89: Rajesh Nair | E89: West | F89: C201 | G89: =VLOOKUP(F89,'CUSTOMER INFO'!B8:D15,2,FALSE) -> TrustCare Medicals | H89: =VLOOKUP(F89,'CUSTOMER INFO'!B8:D15,3,FALSE) -> Pooja Sharma | I89: Hand Sanitizer 200ml | J89: B20HS23 | K89: 46115 | L89: 25 | M89: 22 | N89: =L89*M89 -> 550 | O89: =IF(L89>=60,"Y","N") -> N | P89: =IF(L89>=60,0.95*N89,N89) -> 550
A90: 187 | B90: 45469 | C90: =TEXT(B90,"mmm") -> Jun | D90: Neha Singh | E90: South | F90: C245 | G90: =VLOOKUP(F90,'CUSTOMER INFO'!B9:D16,2,FALSE) -> Lifeline Medicals | H90: =VLOOKUP(F90,'CUSTOMER INFO'!B9:D16,3,FALSE) -> Harshal Singh | I90: ORS Powder | J90: B23OR04 | K90: 46178 | L90: 35 | M90: 48 | N90: =L90*M90 -> 1680 | O90: =IF(L90>=60,"Y","N") -> N | P90: =IF(L90>=60,0.95*N90,N90) -> 1680
A91: 188 | B91: 45470 | C91: =TEXT(B91,"mmm") -> Jun | D91: Adity Rao | E91: East | F91: C160 | G91: =VLOOKUP(F91,'CUSTOMER INFO'!B10:D17,2,FALSE) -> CarePlus Medical Store | H91: =VLOOKUP(F91,'CUSTOMER INFO'!B10:D17,3,FALSE) -> Riya Mishra | I91: Zinc Tablets | J91: B22ZC08 | K91: 46297 | L91: 22 | M91: 95 | N91: =L91*M91 -> 2090 | O91: =IF(L91>=60,"Y","N") -> N | P91: =IF(L91>=60,0.95*N91,N91) -> 2090
A92: 189 | B92: 45471 | C92: =TEXT(B92,"mmm") -> Jun | D92: Priya Mehta | E92: North | F92: C101 | G92: =VLOOKUP(F92,'CUSTOMER INFO'!B3:D10,2,FALSE) -> Shree Medical & General Store | H92: =VLOOKUP(F92,'CUSTOMER INFO'!B3:D10,3,FALSE) -> Abhijeet Kulkarni | I92: Vitamin D3 60k | J92: B21VD63 | K92: 46357 | L92: 62 | M92: 18 | N92: =L92*M92 -> 1116 | O92: =IF(L92>=60,"Y","N") -> Y | P92: =IF(L92>=60,0.95*N92,N92) -> 1060.2
A93: 190 | B93: 45472 | C93: =TEXT(B93,"mmm") -> Jun | D93: Amol Sharma | E93: West | F93: C132 | G93: =VLOOKUP(F93,'CUSTOMER INFO'!B4:D11,2,FALSE) -> JeevanCare Medical Store | H93: =VLOOKUP(F93,'CUSTOMER INFO'!B4:D11,3,FALSE) -> Neha Patel | I93: Antacid Tablets | J93: B21AC07 | K93: 46235 | L93: 32 | M93: 75 | N93: =L93*M93 -> 2400 | O93: =IF(L93>=60,"Y","N") -> N | P93: =IF(L93>=60,0.95*N93,N93) -> 2400
A94: 191 | B94: 45473 | C94: =TEXT(B94,"mmm") -> Jun | D94: Rohit Kholi | E94: South | F94: C140 | G94: =VLOOKUP(F94,'CUSTOMER INFO'!B5:D12,2,FALSE) -> Arogya Medical & General | H94: =VLOOKUP(F94,'CUSTOMER INFO'!B5:D12,3,FALSE) -> Hrishkesh Jadhv | I94: Paracetamol 650mg | J94: B23P652 | K94: 45870 | L94: 65 | M94: 55 | N94: =L94*M94 -> 3575 | O94: =IF(L94>=60,"Y","N") -> Y | P94: =IF(L94>=60,0.95*N94,N94) -> 3396.25
A95: 192 | B95: 45474 | C95: =TEXT(B95,"mmm") -> Jul | D95: Aman Shah | E95: East | F95: C150 | G95: =VLOOKUP(F95,'CUSTOMER INFO'!B6:D13,2,FALSE) -> MedEase | H95: =VLOOKUP(F95,'CUSTOMER INFO'!B6:D13,3,FALSE) -> Siddant Patil | I95: Cough Syrup 100ml | J95: B19CS03 | K95: 46266 | L95: 48 | M95: 32 | N95: =L95*M95 -> 1536 | O95: =IF(L95>=60,"Y","N") -> N | P95: =IF(L95>=60,0.95*N95,N95) -> 1536
A96: 193 | B96: 45475 | C96: =TEXT(B96,"mmm") -> Jul | D96: Komal Sharma | E96: North | F96: C157 | G96: =VLOOKUP(F96,'CUSTOMER INFO'!B7:D14,2,FALSE) -> CityMed Pharmacy | H96: =VLOOKUP(F96,'CUSTOMER INFO'!B7:D14,3,FALSE) -> Vikram Shah | I96: Vitamin C Tablets | J96: B22VC12 | K96: 46357 | L96: 54 | M96: 90 | N96: =L96*M96 -> 4860 | O96: =IF(L96>=60,"Y","N") -> N | P96: =IF(L96>=60,0.95*N96,N96) -> 4860
A97: 194 | B97: 45476 | C97: =TEXT(B97,"mmm") -> Jul | D97: Rajesh Nair | E97: West | F97: C201 | G97: =VLOOKUP(F97,'CUSTOMER INFO'!B8:D15,2,FALSE) -> TrustCare Medicals | H97: =VLOOKUP(F97,'CUSTOMER INFO'!B8:D15,3,FALSE) -> Pooja Sharma | I97: Amoxicillin 500mg | J97: B21AX52 | K97: 46296 | L97: 25 | M97: 20 | N97: =L97*M97 -> 500 | O97: =IF(L97>=60,"Y","N") -> N | P97: =IF(L97>=60,0.95*N97,N97) -> 500
A98: 195 | B98: 45477 | C98: =TEXT(B98,"mmm") -> Jul | D98: Neha Singh | E98: South | F98: C245 | G98: =VLOOKUP(F98,'CUSTOMER INFO'!B9:D16,2,FALSE) -> Lifeline Medicals | H98: =VLOOKUP(F98,'CUSTOMER INFO'!B9:D16,3,FALSE) -> Harshal Singh | I98: Hand Sanitizer 200ml | J98: B20HS22 | K98: 46083 | L98: 35 | M98: 35 | N98: =L98*M98 -> 1225 | O98: =IF(L98>=60,"Y","N") -> N | P98: =IF(L98>=60,0.95*N98,N98) -> 1225
A99: 196 | B99: 45478 | C99: =TEXT(B99,"mmm") -> Jul | D99: Adity Rao | E99: East | F99: C160 | G99: =VLOOKUP(F99,'CUSTOMER INFO'!B10:D17,2,FALSE) -> CarePlus Medical Store | H99: =VLOOKUP(F99,'CUSTOMER INFO'!B10:D17,3,FALSE) -> Riya Mishra | I99: ORS Powder | J99: B23OR03 | K99: 46381 | L99: 38 | M99: 42 | N99: =L99*M99 -> 1596 | O99: =IF(L99>=60,"Y","N") -> N | P99: =IF(L99>=60,0.95*N99,N99) -> 1596
A100: 197 | B100: 45479 | C100: =TEXT(B100,"mmm") -> Jul | D100: Priya Mehta | E100: North | F100: C101 | G100: =VLOOKUP(F100,'CUSTOMER INFO'!B3:D10,2,FALSE) -> Shree Medical & General Store | H100: =VLOOKUP(F100,'CUSTOMER INFO'!B3:D10,3,FALSE) -> Abhijeet Kulkarni | I100: Zinc Tablets | J100: B22ZC07 | K100: 46115 | L100: 28 | M100: 22 | N100: =L100*M100 -> 616 | O100: =IF(L100>=60,"Y","N") -> N | P100: =IF(L100>=60,0.95*N100,N100) -> 616
A101: 198 | B101: 45480 | C101: =TEXT(B101,"mmm") -> Jul | D101: Amol Sharma | E101: West | F101: C132 | G101: =VLOOKUP(F101,'CUSTOMER INFO'!B4:D11,2,FALSE) -> JeevanCare Medical Store | H101: =VLOOKUP(F101,'CUSTOMER INFO'!B4:D11,3,FALSE) -> Neha Patel | I101: Vitamin D3 60k | J101: B21VD62 | K101: 46178 | L101: 54 | M101: 48 | N101: =L101*M101 -> 2592 | O101: =IF(L101>=60,"Y","N") -> N | P101: =IF(L101>=60,0.95*N101,N101) -> 2592
...

Sheet CUSTOMER INFO
B2: Customer ID | C2: Company | D2: Representative
B3: C101 | C3: Shree Medical & General Store | D3: Abhijeet Kulkarni
B4: C132 | C4: JeevanCare Medical Store | D4: Neha Patel
B5: C140 | C5: Arogya Medical & General | D5: Hrishkesh Jadhv
B6: C150 | C6: MedEase | D6: Siddant Patil
B7: C157 | C7: CityMed Pharmacy | D7: Vikram Shah
B8: C201 | C8: TrustCare Medicals | D8: Pooja Sharma
B9: C245 | C9: Lifeline Medicals | D9: Harshal Singh
B10: C160 | C10: CarePlus Medical Store | D10: Riya Mishra
G60: =VLOOKUP(F60,'CUSTOMER INFO'!B3:D10,2,FALSE) -> #N/A
G366: =VLOOKUP(F366,'CUSTOMER INFO'!B3:D10,2,FALSE) -> #N/A

Sheet ABOUT
A1: FIELD | B1: DETAILS
A2: AUTHOR | B2: RUTUJA SANTOSH SHANKPALE
A3: PROJECT TITLE | B3: GUIDED PROJECT: INTRODUCTION TO DATA ANALYSIS USING MICROSOFT EXCEL
A4: COURSE/SOURCE | B4: COURSERA
A5: INSTRUCTOR | B5: PAULA DEL REY
A6: CREATED ON | B6: 45990
A7: CONTACT | B7: www.linkedin.com/in/rutujashankpale
A8: COPYRIGHT | B8: © 2025 RUTUJA SHANKPALE. ORIGINAL WORK. ALL RIGHTS RESERVED.
